bkankur/__init__.py
bkankur/catalog.py
bkankur/config.py
bkankur/demo_batch.py
bkankur/demo_runtime.py
bkankur/evaluator.py
bkankur/models.py
bkankur/parsing.py
bkankur/prompts.py
bkankur/reporting.py
bkankur/schema.py
bkankur/utils.py
bkankur/version.py
bkankur/judges/__init__.py
bkankur/judges/adapters.py
bkankur/judges/base.py
bkankur/judges/generic.py
bkankur/judges/openai_compatible_chat.py
bkankur/judges/openai_responses.py
bkankur-0.1.2.dist-info/METADATA
bkankur-0.1.2.dist-info/WHEEL
bkankur-0.1.2.dist-info/top_level.txt
bkankur-0.1.2.dist-info/RECORD
