Metadata-Version: 2.4
Name: bkankur
Version: 0.1.2
Summary: Protocol-based RAI evaluator with pluggable LLM judges (OpenAI-compatible, etc.)
Author: Ankur Chaturvedi
License: Apache-2.0
Project-URL: Homepage, https://github.com/<your_org>/<your_repo>
Project-URL: Issues, https://github.com/<your_org>/<your_repo>/issues
Keywords: llm,evaluation,rai,safety,governance,judge
Classifier: Development Status :: 4 - Beta
Classifier: Intended Audience :: Developers
Classifier: License :: OSI Approved :: Apache Software License
Classifier: Programming Language :: Python :: 3
Classifier: Programming Language :: Python :: 3 :: Only
Requires-Python: >=3.10
Requires-Dist: pydantic>=2.0
Requires-Dist: httpx>=0.24
